yaml_rs/__init__.py
yaml_rs/_lib.py
yaml_rs/_yaml_rs.cpython-310-aarch64-linux-gnu.so
yaml_rs/_yaml_rs.pyi
yaml_rs/py.typed
yaml_rs-0.0.11.dist-info/METADATA
yaml_rs-0.0.11.dist-info/WHEEL
yaml_rs-0.0.11.dist-info/licenses/UNLICENSE
yaml_rs.libs/libgcc_s-39080030.so.1
yaml_rs-0.0.11.dist-info/RECORD
