Metadata-Version: 2.4
Name: yaml-rs
Version: 0.0.11
Classifier: Typing :: Typed
Classifier: Programming Language :: Rust
Classifier: Programming Language :: Python
Classifier: Programming Language :: Python :: 3
Classifier: Programming Language :: Python :: 3.10
Classifier: Programming Language :: Python :: 3.11
Classifier: Programming Language :: Python :: 3.12
Classifier: Programming Language :: Python :: 3.13
Classifier: Programming Language :: Python :: 3.14
Classifier: Programming Language :: Python :: Implementation :: PyPy
Classifier: Programming Language :: Python :: Implementation :: CPython
Classifier: Topic :: Software Development :: Libraries
Classifier: License :: OSI Approved :: The Unlicense (Unlicense)
License-File: UNLICENSE
Summary: A High-Performance YAML Parser for Python written in Rust
Author-email: chirizxc <chirizxc@proton.me>
Maintainer-email: chirizxc <chirizxc@proton.me>
License-Expression: UNLICENSE
Requires-Python: >=3.10
Project-URL: Bug Tracker, https://github.com/lava-sh/yaml-rs/issues
Project-URL: Homepage, https://github.com/lava-sh/yaml-rs
Project-URL: Source, https://github.com/lava-sh/yaml-rs
